{"_ts":[1543705941,1543792442],"_r":{"breakdown":{"html":{"bytes":[45591,45591],"requests":[5,5]},"js":{"bytes":[218246,218246],"requests":[14,14]},"css":{"bytes":[0,0],"requests":[0,0]},"image":{"bytes":[960,960],"requests":[2,2]},"flash":{"bytes":[0,0],"requests":[0,0]},"font":{"bytes":[0,0],"requests":[0,0]},"video":{"bytes":[0,0],"requests":[0,0]},"other":{"bytes":[195,195],"requests":[1,1]}},"date":[1543705941,1543792442],"domElements":[155,155],"domInteractive":[610,627],"firstPaint":[328.4000000001,333.5],"fullyLoaded":[1345,1417],"id":["181201_6D_f6f533a677b6a4305786dff602aeb9f1","181202_1R_29fa463ab4e3164a005942d684b385c5"],"loadTime":[1183,1250],"render":[400,300],"SpeedIndex":[406,304],"TTFB":[209,221],"videoFrames":[[{"_i":"ms_000000.jpg","_t":0,"_vc":0},{"_i":"ms_000400.jpg","_t":400,"_vc":98},{"_i":"ms_000700.jpg","_t":700,"_vc":100}],[{"_i":"ms_000000.jpg","_t":0,"_vc":0},{"_i":"ms_000300.jpg","_t":300,"_vc":98},{"_i":"ms_000400.jpg","_t":400,"_vc":99},{"_i":"ms_000600.jpg","_t":600,"_vc":100}]],"visualComplete":[700,600],"lighthouse":[85,85],"pagespeed":[null,null]}}