{"_ts":[1509521666,1509563552,1509609361],"_r":{"breakdown":{"html":{"bytes":[86928,86858,66517],"requests":[7,7,10]},"js":{"bytes":[198362,198368,216273],"requests":[16,16,17]},"css":{"bytes":[1388,1388,0],"requests":[2,2,0]},"image":{"bytes":[19194,18787,1722],"requests":[8,8,4]},"flash":{"bytes":[0,0,0],"requests":[0,0,0]},"font":{"bytes":[31161,31161,0],"requests":[2,2,0]},"video":{"bytes":[0,0,0],"requests":[0,0,0]},"other":{"bytes":[0,0,0],"requests":[0,0,0]}},"date":[1509521666,1509563552,1509609361],"domElements":[139,139,140],"domInteractive":[619,508,531],"firstPaint":[355,323,338],"fullyLoaded":[2063,2016,2121],"id":["171101_55_f82723a5e261569ca589c5f7b468110d","171101_C9_9383bc30d4aa73b437f906fc66065661","171102_QA_f9970ffee0ff901e98e0faf924d94ee8"],"loadTime":[1998,1955,1752],"render":[389,386,391],"SpeedIndex":[400,400,400],"TTFB":[238,220,241],"videoFrames":[[{"_i":"frame_0000.jpg","_t":0,"_vc":0},{"_i":"frame_0004.jpg","_t":400,"_vc":100}],[{"_i":"frame_0000.jpg","_t":0,"_vc":0},{"_i":"frame_0004.jpg","_t":400,"_vc":100}],[{"_i":"frame_0000.jpg","_t":0,"_vc":0},{"_i":"frame_0004.jpg","_t":400,"_vc":100}]],"visualComplete":[400,400,400],"lighthouse":[null,null,null],"pagespeed":[98,98,98]}}